odoo8_addon_stock_picking_invoicing-8.0.1.0.0.99.dev11-py2.7-nspkg.pth
odoo_addons/stock_picking_invoicing/stock.py
odoo_addons/stock_picking_invoicing/__openerp__.py
odoo_addons/stock_picking_invoicing/__init__.py
odoo_addons/stock_picking_invoicing/README.rst
odoo_addons/stock_picking_invoicing/stock_view.xml
odoo_addons/stock_picking_invoicing/i18n/tr_TR.po
odoo_addons/stock_picking_invoicing/i18n/pt.po
odoo_addons/stock_picking_invoicing/i18n/it.po
odoo_addons/stock_picking_invoicing/i18n/es.po
odoo_addons/stock_picking_invoicing/i18n/tr.po
odoo_addons/stock_picking_invoicing/i18n/hr.po
odoo_addons/stock_picking_invoicing/i18n/ca.po
odoo_addons/stock_picking_invoicing/i18n/sl.po
odoo_addons/stock_picking_invoicing/i18n/de.po
odoo_addons/stock_picking_invoicing/i18n/fr.po
odoo_addons/stock_picking_invoicing/i18n/pt_BR.po
odoo_addons/stock_picking_invoicing/i18n/es_MX.po
odoo_addons/stock_picking_invoicing/i18n/fi.po
odoo_addons/stock_picking_invoicing/tests/test_picking_invoicing.py
odoo_addons/stock_picking_invoicing/tests/__init__.py
odoo_addons/stock_picking_invoicing/static/description/icon.png
odoo8_addon_stock_picking_invoicing-8.0.1.0.0.99.dev11.dist-info/top_level.txt
odoo8_addon_stock_picking_invoicing-8.0.1.0.0.99.dev11.dist-info/WHEEL
odoo8_addon_stock_picking_invoicing-8.0.1.0.0.99.dev11.dist-info/RECORD
odoo8_addon_stock_picking_invoicing-8.0.1.0.0.99.dev11.dist-info/metadata.json
odoo8_addon_stock_picking_invoicing-8.0.1.0.0.99.dev11.dist-info/DESCRIPTION.rst
odoo8_addon_stock_picking_invoicing-8.0.1.0.0.99.dev11.dist-info/METADATA
odoo8_addon_stock_picking_invoicing-8.0.1.0.0.99.dev11.dist-info/namespace_packages.txt
