Metadata-Version: 2.0
Name: odoo8-addon-stock-picking-invoicing
Version: 8.0.1.0.0.99.dev11
Summary: Stock Picking Invoicing
Home-page: http://www.agilebg.com
Author: Agile Business Group,Odoo Community Association (OCA)
Author-email: support@odoo-community.org
License: AGPL-3
Platform: UNKNOWN
Requires-Dist: odoo (<9.0a,>=8.0a)
Requires-Dist: odoo8-addon-stock-picking-invoice-link
Classifier: Programming Language :: Python :: 2.7
Classifier: Framework :: Odoo
Classifier: License :: OSI Approved :: GNU Affero General Public License v3
